<?xml version="1.0" encoding="utf-8"?>

<!--
Map pack from AnyGIS.ru
Updated: 29-02-2020 21:16
-->



<locusActions>

<download>
<source>
<![CDATA[https://github.com/nnngrach/AnyGIS_maps/raw/master/Locus_online_maps/Icons_en/Overlay%20-%20Info%20-%20Europe%20-%20Eastern.png]]>
</source>
<dest>
<![CDATA[/mapsOnline/custom/Overlay - Info - Europe - Eastern.png]]>
</dest>
</download>

<download>
<source>
<![CDATA[https://raw.githubusercontent.com/nnngrach/AnyGIS_maps/master/Locus_online_maps/Maps_full_en/=Overlay=Info=EU=East=CadastrUA_overlay.xml]]>
</source>
<dest>
<![CDATA[/mapsOnline/custom/=Overlay=Info=EU=East=CadastrUA_overlay.xml]]>
</dest>
</download>

</locusActions>