<?xml version="1.0" encoding="utf-8"?>

<!--
Map pack from AnyGIS.ru
Updated: 01-03-2020 14:10
-->



<locusActions>

<download>
<source>
<![CDATA[https://github.com/nnngrach/AnyGIS_maps/raw/master/Locus_online_maps/Icons_en/Satellites%20-%20America.png]]>
</source>
<dest>
<![CDATA[/mapsOnline/custom/Satellites - America.png]]>
</dest>
</download>

<download>
<source>
<![CDATA[https://raw.githubusercontent.com/nnngrach/AnyGIS_maps/master/Locus_online_maps/Maps_full_en/=Satellites=US=USGS_Sat.xml]]>
</source>
<dest>
<![CDATA[/mapsOnline/custom/=Satellites=US=USGS_Sat.xml]]>
</dest>
</download>

<download>
<source>
<![CDATA[https://raw.githubusercontent.com/nnngrach/AnyGIS_maps/master/Locus_online_maps/Maps_full_en/=Satellites=US=USGS_Sat_plus.xml]]>
</source>
<dest>
<![CDATA[/mapsOnline/custom/=Satellites=US=USGS_Sat_plus.xml]]>
</dest>
</download>

</locusActions>